biomaj_user/__init__.py
biomaj_user/biomaj_user_service.py
biomaj_user/user.py
biomaj_user/wsgi.py
biomaj_user-3.0.12.data/scripts/biomaj-users.py
biomaj_user-3.0.12.dist-info/LICENSE
biomaj_user-3.0.12.dist-info/METADATA
biomaj_user-3.0.12.dist-info/WHEEL
biomaj_user-3.0.12.dist-info/top_level.txt
biomaj_user-3.0.12.dist-info/RECORD
