Metadata-Version: 2.1
Name: biomaj-user
Version: 3.0.12
Summary: BioMAJ user management library
Home-page: http://biomaj.genouest.org
Author: Olivier Sallou
Author-email: olivier.sallou@irisa.fr
License: UNKNOWN
Download-URL: http://biomaj.genouest.org
Platform: UNKNOWN
Classifier: Development Status :: 5 - Production/Stable
Classifier: Environment :: Console
Classifier: Natural Language :: English
Classifier: Operating System :: POSIX :: Linux
Classifier: Intended Audience :: Science/Research
Classifier: Topic :: Scientific/Engineering :: Bio-Informatics
Classifier: License :: OSI Approved :: GNU Affero General Public License v3 or later (AGPLv3+)
Classifier: Programming Language :: Python :: 3
License-File: LICENSE
Requires-Dist: ldap3 (>=2.2.4)
Requires-Dist: pymongo (<4,>=3.12.3)
Requires-Dist: py-bcrypt
Requires-Dist: flask
Requires-Dist: PyYAML
Requires-Dist: tabulate
Requires-Dist: python-consul
Requires-Dist: biomaj-core
